server/__init__.py
server/__main__.py
server/app.py
hangpt_cpp-0.1.dist-info/METADATA
hangpt_cpp-0.1.dist-info/WHEEL
hangpt_cpp-0.1.dist-info/top_level.txt
hangpt_cpp-0.1.dist-info/RECORD
